.coveragerc
.travis.yml
LICENSE
MANIFEST.in
README.rst
setup.cfg
setup.py
Mopidy_GPIO.egg-info/PKG-INFO
Mopidy_GPIO.egg-info/SOURCES.txt
Mopidy_GPIO.egg-info/dependency_links.txt
Mopidy_GPIO.egg-info/entry_points.txt
Mopidy_GPIO.egg-info/not-zip-safe
Mopidy_GPIO.egg-info/requires.txt
Mopidy_GPIO.egg-info/top_level.txt
mopidy_gpio/__init__.py
mopidy_gpio/backend.py
mopidy_gpio/ext.conf
mopidy_gpio/manager.py