Metadata-Version: 1.1
Name: Mopidy-GPIO
Version: 0.1.15
Summary: Controll mopidy with GPIO
Home-page: https://github.com/Kriez/Mopidy-GPIO
Author: Kriez
Author-email: per.stromgren@gmail.com
License: Apache License, Version 2.0
Platform: UNKNOWN
Classifier: Environment :: No Input/Output (Daemon)
Classifier: Intended Audience :: End Users/Desktop
Classifier: License :: OSI Approved :: Apache Software License
Classifier: Operating System :: OS Independent
Classifier: Programming Language :: Python :: 2
Classifier: Topic :: Multimedia :: Sound/Audio :: Players
